mcpuppeteer-0.0.3.dist-info/licenses/LICENSE
puppet/__init__.py
puppet/connection.py
puppet/constants.py
puppet/player.py
puppet/world.py
mcpuppeteer-0.0.3.dist-info/METADATA
mcpuppeteer-0.0.3.dist-info/WHEEL
mcpuppeteer-0.0.3.dist-info/top_level.txt
mcpuppeteer-0.0.3.dist-info/RECORD
