Metadata-Version: 2.4
Name: McPuppeteer
Version: 0.0.3
Summary: A python library for fully controlling the player in Minecraft
Home-page: https://github.com/PsychedelicPalimpsest/PyMcPuppeteer
Author: PsychedelicPalimpsest
License: GPLv3
Classifier: Intended Audience :: Developers
Classifier: License :: OSI Approved :: GNU General Public License v3 (GPLv3)
Classifier: Operating System :: OS Independent
Classifier: Programming Language :: Python :: 3
Classifier: Topic :: Games/Entertainment
Classifier: Topic :: Software Development :: Libraries :: Python Modules
License-File: LICENSE
Requires-Dist: nbtlib==1.12.1
Dynamic: author
Dynamic: classifier
Dynamic: description
Dynamic: description-content-type
Dynamic: home-page
Dynamic: license
Dynamic: license-file
Dynamic: requires-dist
Dynamic: summary
